legit_every_pip_library_i_own/__init__.py
legit_every_pip_library_i_own-0.1.0.dist-info/METADATA
legit_every_pip_library_i_own-0.1.0.dist-info/WHEEL
legit_every_pip_library_i_own-0.1.0.dist-info/top_level.txt
legit_every_pip_library_i_own-0.1.0.dist-info/RECORD
